bitcoinInitialize.py
BitcoinAlert-0.1.dist-info/LICENSE.txt
BitcoinAlert-0.1.dist-info/METADATA
BitcoinAlert-0.1.dist-info/WHEEL
BitcoinAlert-0.1.dist-info/top_level.txt
BitcoinAlert-0.1.dist-info/RECORD
